{
    "nodes": [
        {
            "edge_coexisting": [
                475,
                529,
                583,
                602,
                622,
                712,
                751,
                583,
                602,
                622,
                712,
                751
            ],
            "package_id": 549,
            "OSS": "RubyGems",
            "Source": "Backstabber-Knife",
            "Status": "untracked",
            "filepath": "https://dasfreak.github.io/Backstabbers-Knife-Collection/",
            "package_name": "capistrano-colors",
            "sourcecode_hash": null,
            "dependency": null,
            "source_publish": "2020-05-19T",
            "API_Use": null,
            "Tokens_num": null,
            "Embedding_vector": null,
            "Cluster_type": null,
            "Report": "['https://helpnetsecurity.com/2019/08/21/backdoored-ruby-gems/']",
            "edge_name": [],
            "edge_codehash": [],
            "edge_dependency": [],
            "edge_similar": [],
            "id": 549
        },
        {
            "package_id": 475,
            "OSS": "RubyGems",
            "Source": "Backstabber-Knife",
            "Status": "untracked",
            "filepath": "https://dasfreak.github.io/Backstabbers-Knife-Collection/",
            "package_name": "awesome-bot",
            "sourcecode_hash": null,
            "dependency": null,
            "source_publish": "2020-05-19T",
            "API_Use": null,
            "Tokens_num": null,
            "Embedding_vector": null,
            "Cluster_type": null,
            "Report": "['https://helpnetsecurity.com/2019/08/21/backdoored-ruby-gems/']",
            "edge_name": [],
            "edge_codehash": [],
            "edge_dependency": [],
            "edge_similar": [],
            "edge_coexisting": [
                529,
                549,
                583,
                602,
                622,
                712,
                751,
                529,
                549,
                583,
                602,
                622,
                712,
                751
            ],
            "id": 475
        },
        {
            "edge_coexisting": [
                475,
                549,
                583,
                602,
                622,
                712,
                751,
                549,
                583,
                602,
                622,
                712,
                751
            ],
            "package_id": 529,
            "OSS": "RubyGems",
            "Source": "Backstabber-Knife",
            "Status": "untracked",
            "filepath": "https://dasfreak.github.io/Backstabbers-Knife-Collection/",
            "package_name": "blockchain_wallet",
            "sourcecode_hash": null,
            "dependency": null,
            "source_publish": "2020-05-19T",
            "API_Use": null,
            "Tokens_num": null,
            "Embedding_vector": null,
            "Cluster_type": null,
            "Report": "['https://helpnetsecurity.com/2019/08/21/backdoored-ruby-gems/']",
            "edge_name": [],
            "edge_codehash": [],
            "edge_dependency": [],
            "edge_similar": [],
            "id": 529
        },
        {
            "edge_coexisting": [
                475,
                529,
                549,
                602,
                622,
                712,
                751,
                602,
                622,
                712,
                751
            ],
            "package_id": 583,
            "OSS": "RubyGems",
            "Source": "Backstabber-Knife",
            "Status": "untracked",
            "filepath": "https://dasfreak.github.io/Backstabbers-Knife-Collection/",
            "package_name": "coin_base",
            "sourcecode_hash": null,
            "dependency": null,
            "source_publish": "2020-05-19T",
            "API_Use": null,
            "Tokens_num": null,
            "Embedding_vector": null,
            "Cluster_type": null,
            "Report": "['https://helpnetsecurity.com/2019/08/21/backdoored-ruby-gems/']",
            "edge_name": [],
            "edge_codehash": [],
            "edge_dependency": [],
            "edge_similar": [],
            "id": 583
        },
        {
            "edge_coexisting": [
                475,
                529,
                549,
                583,
                622,
                712,
                751,
                622,
                712,
                751
            ],
            "package_id": 602,
            "OSS": "RubyGems",
            "Source": "Backstabber-Knife",
            "Status": "untracked",
            "filepath": "https://dasfreak.github.io/Backstabbers-Knife-Collection/",
            "package_name": "cron_parser",
            "sourcecode_hash": null,
            "dependency": null,
            "source_publish": "2020-05-19T",
            "API_Use": null,
            "Tokens_num": null,
            "Embedding_vector": null,
            "Cluster_type": null,
            "Report": "['https://helpnetsecurity.com/2019/08/21/backdoored-ruby-gems/']",
            "edge_name": [],
            "edge_codehash": [],
            "edge_dependency": [],
            "edge_similar": [],
            "id": 602
        },
        {
            "edge_coexisting": [
                475,
                529,
                549,
                583,
                602,
                712,
                751,
                712,
                751
            ],
            "package_id": 622,
            "OSS": "RubyGems",
            "Source": "Backstabber-Knife",
            "Status": "untracked",
            "filepath": "https://dasfreak.github.io/Backstabbers-Knife-Collection/",
            "package_name": "doge-coin",
            "sourcecode_hash": null,
            "dependency": null,
            "source_publish": "2020-05-19T",
            "API_Use": null,
            "Tokens_num": null,
            "Embedding_vector": null,
            "Cluster_type": null,
            "Report": "['https://helpnetsecurity.com/2019/08/21/backdoored-ruby-gems/']",
            "edge_name": [],
            "edge_codehash": [],
            "edge_dependency": [],
            "edge_similar": [],
            "id": 622
        },
        {
            "edge_coexisting": [
                475,
                529,
                549,
                583,
                602,
                622,
                751,
                751
            ],
            "package_id": 712,
            "OSS": "RubyGems",
            "Source": "Backstabber-Knife",
            "Status": "untracked",
            "filepath": "https://dasfreak.github.io/Backstabbers-Knife-Collection/",
            "package_name": "lita_coin",
            "sourcecode_hash": null,
            "dependency": null,
            "source_publish": "2020-05-19T",
            "API_Use": null,
            "Tokens_num": null,
            "Embedding_vector": null,
            "Cluster_type": null,
            "Report": "['https://helpnetsecurity.com/2019/08/21/backdoored-ruby-gems/']",
            "edge_name": [],
            "edge_codehash": [],
            "edge_dependency": [],
            "edge_similar": [],
            "id": 712
        },
        {
            "edge_coexisting": [
                475,
                529,
                549,
                583,
                602,
                622,
                712
            ],
            "package_id": 751,
            "OSS": "RubyGems",
            "Source": "Backstabber-Knife",
            "Status": "untracked",
            "filepath": "https://dasfreak.github.io/Backstabbers-Knife-Collection/",
            "package_name": "omniauth_amazon",
            "sourcecode_hash": null,
            "dependency": null,
            "source_publish": "2020-05-19T",
            "API_Use": null,
            "Tokens_num": null,
            "Embedding_vector": null,
            "Cluster_type": null,
            "Report": "['https://helpnetsecurity.com/2019/08/21/backdoored-ruby-gems/']",
            "edge_name": [],
            "edge_codehash": [],
            "edge_dependency": [],
            "edge_similar": [],
            "id": 751
        }
    ]
}