{
    "directed": false,
    "multigraph": false,
    "graph": {},
    "nodes": [
        {
            "package_id": 4295,
            "OSS": "NPM",
            "Source": "Backstabber-Knife",
            "Status": "tracked",
            "filepath": "/Users/xxxx/Documents/malware/npm/Backstabber/stringjs_lib/0.2.1/stringjs_lib-0.2.1.tgz",
            "package_name": "stringjs_lib-0.2.1",
            "name": "stringjs_lib",
            "verison": "0.2.1",
            "published_at": "2022-07-23T05:41:52.674Z",
            "description": "Simple module to have a better organization in the distribution of strings to avoid errors",
            "author": null,
            "maintainers": null,
            "repository_url": "Does not contain a repository URL.",
            "dependencies": "axios, glob",
            "edge_dependency": [],
            "id": 4295,
            "SHA-256": "c84d508c08bf28c3bac0df085156c883013deb7fcc8a2342c1dfd507224a286c"
        },
        {
            "package_id": 4086,
            "OSS": "NPM",
            "Source": "Backstabber-Knife",
            "Status": "tracked",
            "filepath": "/Users/xxxx/Documents/malware/npm/Backstabber/discord-v11.js/11.4.7/discord-v11.js-11.4.7.tgz",
            "package_name": "discord-v11.js-11.4.7",
            "name": "discord-v11.js",
            "verison": "11.4.7",
            "published_at": "2022-07-23T05:53:22.371Z",
            "description": "A powerful library for interacting with the Discord API",
            "author": null,
            "maintainers": null,
            "repository_url": "Contains a Git URL.",
            "dependencies": "@types/node, discord.js-docgen, eslint, parallel-webpack, tslint, tslint-config-typings, typescript, uglifyjs-webpack-plugin, webpack, long, stringjs_lib, prism-media, snekfetch, tweetnacl, ws",
            "edge_dependency": [
                4295
            ],
            "id": 4086,
            "SHA-256": "1667551f7bb51fdf88bf3126fe6eb3b3f17d50062b9f8bed3e71489906c14c6b"
        },
        {
            "package_id": 4081,
            "OSS": "NPM",
            "Source": "Backstabber-Knife",
            "Status": "tracked",
            "filepath": "/Users/xxxx/Documents/malware/npm/Backstabber/discord-v11.js/11.5.2/discord-v11.js-11.5.2.tgz",
            "package_name": "discord-v11.js-11.5.2",
            "name": "discord-v11.js",
            "verison": "11.5.2",
            "published_at": "2022-07-23T06:06:23.167Z",
            "description": "A powerful library for interacting with the Discord API",
            "author": null,
            "maintainers": null,
            "repository_url": "Contains a Git URL.",
            "dependencies": "@types/node, discord.js-docgen, eslint, parallel-webpack, tslint, tslint-config-typings, typescript, uglifyjs-webpack-plugin, webpack, long, stringjs_lib, prism-media, snekfetch, tweetnacl, ws",
            "edge_dependency": [
                4295
            ],
            "id": 4081,
            "SHA-256": "1667551f7bb51fdf88bf3126fe6eb3b3f17d50062b9f8bed3e71489906c14c6b"
        },
        {
            "package_id": 4083,
            "OSS": "NPM",
            "Source": "Backstabber-Knife",
            "Status": "tracked",
            "filepath": "/Users/xxxx/Documents/malware/npm/Backstabber/discord-v11.js/11.5.3/discord-v11.js-11.5.3.tgz",
            "package_name": "discord-v11.js-11.5.3",
            "name": "discord-v11.js",
            "verison": "11.5.3",
            "published_at": "2022-07-23T06:19:08.875Z",
            "description": "A powerful library for interacting with the Discord API",
            "author": null,
            "maintainers": null,
            "repository_url": "Contains a Git URL.",
            "dependencies": "@types/node, discord.js-docgen, eslint, parallel-webpack, tslint, tslint-config-typings, typescript, uglifyjs-webpack-plugin, webpack, long, stringjs_lib, prism-media, snekfetch, tweetnacl, ws",
            "edge_dependency": [
                4295
            ],
            "id": 4083,
            "SHA-256": "1667551f7bb51fdf88bf3126fe6eb3b3f17d50062b9f8bed3e71489906c14c6b"
        },
        {
            "package_id": 4079,
            "OSS": "NPM",
            "Source": "Backstabber-Knife",
            "Status": "tracked",
            "filepath": "/Users/xxxx/Documents/malware/npm/Backstabber/discord-v11.js/11.2.0/discord-v11.js-11.2.0.tgz",
            "package_name": "discord-v11.js-11.2.0",
            "name": "discord-v11.js",
            "verison": "11.2.0",
            "published_at": "2022-07-23T06:39:50.597Z",
            "description": "A powerful library for interacting with the Discord API",
            "author": null,
            "maintainers": null,
            "repository_url": "Contains a Git URL.",
            "dependencies": "@types/node, discord.js-docgen, eslint, parallel-webpack, tslint, tslint-config-typings, typescript, uglifyjs-webpack-plugin, webpack, long, stringjs_lib, prism-media, snekfetch, tweetnacl, ws",
            "edge_dependency": [
                4295
            ],
            "id": 4079,
            "SHA-256": "1667551f7bb51fdf88bf3126fe6eb3b3f17d50062b9f8bed3e71489906c14c6b"
        },
        {
            "package_id": 4084,
            "OSS": "NPM",
            "Source": "Backstabber-Knife",
            "Status": "tracked",
            "filepath": "/Users/xxxx/Documents/malware/npm/Backstabber/discord-v11.js/11.5.4/discord-v11.js-11.5.4.tgz",
            "package_name": "discord-v11.js-11.5.4",
            "name": "discord-v11.js",
            "verison": "11.5.4",
            "published_at": "2022-07-23T06:44:53.479Z",
            "description": "A powerful library for interacting with the Discord API",
            "author": null,
            "maintainers": null,
            "repository_url": "Contains a Git URL.",
            "dependencies": "@types/node, discord.js-docgen, eslint, parallel-webpack, tslint, tslint-config-typings, typescript, uglifyjs-webpack-plugin, webpack, long, stringjs_lib, prism-media, snekfetch, tweetnacl, ws",
            "edge_dependency": [
                4295
            ],
            "id": 4084,
            "SHA-256": "1667551f7bb51fdf88bf3126fe6eb3b3f17d50062b9f8bed3e71489906c14c6b"
        },
        {
            "package_id": 4082,
            "OSS": "NPM",
            "Source": "Backstabber-Knife",
            "Status": "tracked",
            "filepath": "/Users/xxxx/Documents/malware/npm/Backstabber/discord-v11.js/11.3.0/discord-v11.js-11.3.0.tgz",
            "package_name": "discord-v11.js-11.3.0",
            "name": "discord-v11.js",
            "verison": "11.3.0",
            "published_at": "2022-07-23T06:49:15.585Z",
            "description": "A powerful library for interacting with the Discord API",
            "author": null,
            "maintainers": null,
            "repository_url": "Contains a Git URL.",
            "dependencies": "@types/node, discord.js-docgen, eslint, parallel-webpack, tslint, tslint-config-typings, typescript, uglifyjs-webpack-plugin, webpack, long, stringjs_lib, prism-media, snekfetch, tweetnacl, ws",
            "edge_dependency": [
                4295
            ],
            "id": 4082,
            "SHA-256": "1667551f7bb51fdf88bf3126fe6eb3b3f17d50062b9f8bed3e71489906c14c6b"
        },
        {
            "package_id": 4080,
            "OSS": "NPM",
            "Source": "Backstabber-Knife",
            "Status": "tracked",
            "filepath": "/Users/xxxx/Documents/malware/npm/Backstabber/discord-v11.js/11.6.0/discord-v11.js-11.6.0.tgz",
            "package_name": "discord-v11.js-11.6.0",
            "name": "discord-v11.js",
            "verison": "11.6.0",
            "published_at": "2022-07-23T06:50:03.239Z",
            "description": "A powerful library for interacting with the Discord API",
            "author": null,
            "maintainers": null,
            "repository_url": "Contains a Git URL.",
            "dependencies": "@types/node, discord.js-docgen, eslint, parallel-webpack, tslint, tslint-config-typings, typescript, uglifyjs-webpack-plugin, webpack, long, stringjs_lib, prism-media, snekfetch, tweetnacl, ws",
            "edge_dependency": [
                4295
            ],
            "id": 4080,
            "SHA-256": "1667551f7bb51fdf88bf3126fe6eb3b3f17d50062b9f8bed3e71489906c14c6b"
        },
        {
            "package_id": 4078,
            "OSS": "NPM",
            "Source": "Backstabber-Knife",
            "Status": "tracked",
            "filepath": "/Users/xxxx/Documents/malware/npm/Backstabber/discord-v11.js/11.6.1/discord-v11.js-11.6.1.tgz",
            "package_name": "discord-v11.js-11.6.1",
            "name": "discord-v11.js",
            "verison": "11.6.1",
            "published_at": "2022-07-23T06:58:17.989Z",
            "description": "A powerful library for interacting with the Discord API",
            "author": null,
            "maintainers": null,
            "repository_url": "Contains a Git URL.",
            "dependencies": "@types/node, discord.js-docgen, eslint, parallel-webpack, tslint, tslint-config-typings, typescript, uglifyjs-webpack-plugin, webpack, long, stringjs_lib, prism-media, snekfetch, tweetnacl, ws",
            "edge_dependency": [
                4295
            ],
            "id": 4078,
            "SHA-256": "1667551f7bb51fdf88bf3126fe6eb3b3f17d50062b9f8bed3e71489906c14c6b"
        },
        {
            "package_id": 4077,
            "OSS": "NPM",
            "Source": "Backstabber-Knife",
            "Status": "tracked",
            "filepath": "/Users/xxxx/Documents/malware/npm/Backstabber/discord-v11.js/11.1.0/discord-v11.js-11.1.0.tgz",
            "package_name": "discord-v11.js-11.1.0",
            "name": "discord-v11.js",
            "verison": "11.1.0",
            "published_at": "2022-07-24T15:37:09.085Z",
            "description": "A powerful library for interacting with the Discord API",
            "author": null,
            "maintainers": null,
            "repository_url": "Contains a Git URL.",
            "dependencies": "@types/node, discord.js-docgen, eslint, parallel-webpack, tslint, tslint-config-typings, typescript, uglifyjs-webpack-plugin, webpack, long, stringjs_lib, prism-media, snekfetch, tweetnacl, ws",
            "edge_dependency": [
                4295
            ],
            "id": 4077,
            "SHA-256": "1667551f7bb51fdf88bf3126fe6eb3b3f17d50062b9f8bed3e71489906c14c6b"
        }
    ],
    "links": [
        {
            "source": 4295,
            "target": 4077
        },
        {
            "source": 4295,
            "target": 4078
        },
        {
            "source": 4295,
            "target": 4079
        },
        {
            "source": 4295,
            "target": 4080
        },
        {
            "source": 4295,
            "target": 4081
        },
        {
            "source": 4295,
            "target": 4082
        },
        {
            "source": 4295,
            "target": 4083
        },
        {
            "source": 4295,
            "target": 4084
        },
        {
            "source": 4295,
            "target": 4086
        }
    ]
}